{
  "generated_at": "2026-06-17 20:00:42",
  "source_file": "GMEC-Downy_全品牌数据Raw-当天_20260617_20260617.csv",
  "slot_label": "2002",
  "report_date": "2026-06-17",
  "sku_count": 22,
  "skus": [
    {
      "账户": "GMEC-Ariel",
      "SKU名称": "碧浪洗衣免搓粉 纯净清香6.2斤装 洗衣粉非爆炸盐皂粉  99%杀菌除螨",
      "SKU简称": "碧浪免搓粉3.1kg",
      "SKU ID": "100161952438",
      "综合ROI(含JST+SEM)": 1.75,
      "综合花费(SPD)": 7294.11,
      "综合CPC": 6.13,
      "综合CTR": 0.0706,
      "综合CVR": 0.1968,
      "状态": "🔺 高于目标10%以上",
      "ROI目标": 1.5,
      "JST花费(SPD)": 770.21,
      "JST ROI": 2.37,
      "JST CPC": 3.5169,
      "SEM花费(SPD)": 6523.9,
      "SEM ROI": 1.68,
      "SEM CPC": 6.7257
    },
    {
      "账户": "GMEC-Ariel",
      "SKU名称": "碧浪洗衣免搓粉 阳光薰衣草6.2斤装 洗衣粉非爆炸盐皂粉  99%杀菌除螨",
      "SKU简称": "碧浪薰衣草免搓粉3.1kg",
      "SKU ID": "100162871390",
      "综合ROI(含JST+SEM)": 1.93,
      "综合花费(SPD)": 894.01,
      "综合CPC": 4.73,
      "综合CTR": 0.0392,
      "综合CVR": 0.1534,
      "状态": "🔺 高于目标10%以上",
      "ROI目标": 1.5,
      "JST花费(SPD)": 144.85,
      "JST ROI": 3.56,
      "JST CPC": 2.4142,
      "SEM花费(SPD)": 749.16,
      "SEM ROI": 1.61,
      "SEM CPC": 5.8074
    },
    {
      "账户": "GMEC-Ariel-L",
      "SKU名称": "碧浪除菌洗衣液20斤装(3kg*3瓶自然清新+200g*5袋草本清新)家庭装",
      "SKU简称": "碧浪NF10kg",
      "SKU ID": "100036714440",
      "综合ROI(含JST+SEM)": 2.45,
      "综合花费(SPD)": 5665.89,
      "综合CPC": 11.68,
      "综合CTR": 0.0449,
      "综合CVR": 0.1711,
      "状态": "正常",
      "ROI目标": 2.5,
      "JST花费(SPD)": 64.21,
      "JST ROI": 17.06,
      "JST CPC": 1.9458,
      "SEM花费(SPD)": 5601.68,
      "SEM ROI": 2.29,
      "SEM CPC": 12.3931
    },
    {
      "账户": "GMEC-Ariel-L",
      "SKU名称": "碧浪除菌洗衣液日晒般清新13.6斤装(3kg*2瓶+200g*4袋)家庭装",
      "SKU简称": "碧浪Matic 6.8kg",
      "SKU ID": "4713934",
      "综合ROI(含JST+SEM)": 4.53,
      "综合花费(SPD)": 586.73,
      "综合CPC": 3.19,
      "综合CTR": 0.0605,
      "综合CVR": 0.1739,
      "状态": "🔺 高于目标10%以上",
      "ROI目标": 2.5,
      "JST花费(SPD)": 134.68,
      "JST ROI": 16.57,
      "JST CPC": 1.0051,
      "SEM花费(SPD)": 452.05,
      "SEM ROI": 0.94,
      "SEM CPC": 9.041
    },
    {
      "账户": "GMEC-Ariel-L",
      "SKU名称": "碧浪除菌洗衣液日晒般清新18斤装(3kg*2瓶+500g*6袋)家庭装 根源消臭",
      "SKU简称": "碧浪Matic9kg",
      "SKU ID": "100039735595",
      "综合ROI(含JST+SEM)": 1.87,
      "综合花费(SPD)": 759.22,
      "综合CPC": 4.9,
      "综合CTR": 0.0674,
      "综合CVR": 0.0774,
      "状态": "🔻 低于目标10%以上",
      "ROI目标": 2.5,
      "JST花费(SPD)": 53.56,
      "JST ROI": 6.06,
      "JST CPC": 0.9396,
      "SEM花费(SPD)": 705.66,
      "SEM ROI": 1.55,
      "SEM CPC": 7.2006
    },
    {
      "账户": "GMEC-Ariel-L",
      "SKU名称": "碧浪除菌洗衣液日晒般清新6斤瓶装 杀菌除螨 根源消臭去黄 支持快洗",
      "SKU简称": "碧浪日晒清新6斤",
      "SKU ID": "1978117",
      "综合ROI(含JST+SEM)": 2.02,
      "综合花费(SPD)": 3553.87,
      "综合CPC": 6.26,
      "综合CTR": 0.0737,
      "综合CVR": 0.2201,
      "状态": "🔻 低于目标10%以上",
      "ROI目标": 2.5,
      "JST花费(SPD)": 122.14,
      "JST ROI": 10.5,
      "JST CPC": 1.7449,
      "SEM花费(SPD)": 3431.73,
      "SEM ROI": 1.72,
      "SEM CPC": 6.891
    },
    {
      "账户": "GMEC-Ariel-L",
      "SKU名称": "碧浪除菌洗衣液清雅茉莉12斤瓶装(3kg*2) 杀菌除螨 根源消臭去黄",
      "SKU简称": "碧浪Jasmine6kg",
      "SKU ID": "100008766160",
      "综合ROI(含JST+SEM)": 1.44,
      "综合花费(SPD)": 1645.74,
      "综合CPC": 7.95,
      "综合CTR": 0.0407,
      "综合CVR": 0.1256,
      "状态": "🔻 低于目标10%以上",
      "ROI目标": 2.5,
      "JST花费(SPD)": 64.39,
      "JST ROI": 7.77,
      "JST CPC": 2.6829,
      "SEM花费(SPD)": 1581.35,
      "SEM ROI": 1.18,
      "SEM CPC": 8.6413
    },
    {
      "账户": "GMEC-Ariel-L",
      "SKU名称": "碧浪除菌洗衣液自然清新16斤瓶装(2kg*4) 杀菌除螨 根源消臭去黄",
      "SKU简称": "碧浪自然清香16斤",
      "SKU ID": "100006804447",
      "综合ROI(含JST+SEM)": 1.78,
      "综合花费(SPD)": 1410.1,
      "综合CPC": 8.2,
      "综合CTR": 0.0496,
      "综合CVR": 0.1512,
      "状态": "🔻 低于目标10%以上",
      "ROI目标": 2.5,
      "JST花费(SPD)": 117.8,
      "JST ROI": 11.78,
      "JST CPC": 2.1036,
      "SEM花费(SPD)": 1292.3,
      "SEM ROI": 0.87,
      "SEM CPC": 11.1405
    },
    {
      "账户": "GMEC-Downy",
      "SKU名称": "当妮护衣留香珠清晨橘光450g 12周持久留香防异味 99%除菌除螨 易溶解",
      "SKU简称": "当妮450g清晨橘光",
      "SKU ID": "100268112394",
      "综合ROI(含JST+SEM)": 0.84,
      "综合花费(SPD)": 83.37,
      "综合CPC": 3.09,
      "综合CTR": 0.0487,
      "综合CVR": 0.037,
      "状态": "🔻 低于目标10%以上",
      "ROI目标": 3.0,
      "JST花费(SPD)": 83.37,
      "JST ROI": 0.84,
      "JST CPC": 3.0878,
      "SEM花费(SPD)": 0.0,
      "SEM ROI": 0.0,
      "SEM CPC": 0.0
    },
    {
      "账户": "GMEC-Downy",
      "SKU名称": "当妮护衣留香珠清晨橘光950g 12周持久留香 防异味 99%除菌除螨家庭装",
      "SKU简称": "当妮950g清晨橘光",
      "SKU ID": "100233530169",
      "综合ROI(含JST+SEM)": 2.76,
      "综合花费(SPD)": 307.49,
      "综合CPC": 10.6,
      "综合CTR": 0.0403,
      "综合CVR": 0.069,
      "状态": "正常",
      "ROI目标": 3.0,
      "JST花费(SPD)": 3.52,
      "JST ROI": 0.0,
      "JST CPC": 1.76,
      "SEM花费(SPD)": 303.97,
      "SEM ROI": 2.79,
      "SEM CPC": 11.2581
    },
    {
      "账户": "GMEC-Downy",
      "SKU名称": "当妮护衣留香珠清雨山茶450g 12周持久留香防异味 99%除菌除螨 易溶解",
      "SKU简称": "当妮450g清雨山茶",
      "SKU ID": "100094637928",
      "综合ROI(含JST+SEM)": 1.91,
      "综合花费(SPD)": 560.86,
      "综合CPC": 6.92,
      "综合CTR": 0.0464,
      "综合CVR": 0.1975,
      "状态": "🔻 低于目标10%以上",
      "ROI目标": 3.0,
      "JST花费(SPD)": 525.13,
      "JST ROI": 1.91,
      "JST CPC": 7.6106,
      "SEM花费(SPD)": 35.73,
      "SEM ROI": 1.96,
      "SEM CPC": 2.9775
    },
    {
      "账户": "GMEC-Downy",
      "SKU名称": "当妮护衣留香珠玫瑰之巅450g 12周持久留香防异味 99%除菌除螨 易溶解",
      "SKU简称": "当妮450g玫瑰之巅",
      "SKU ID": "100044243858",
      "综合ROI(含JST+SEM)": 2.98,
      "综合花费(SPD)": 2236.17,
      "综合CPC": 5.45,
      "综合CTR": 0.0583,
      "综合CVR": 0.1829,
      "状态": "正常",
      "ROI目标": 3.0,
      "JST花费(SPD)": 1110.59,
      "JST ROI": 3.81,
      "JST CPC": 4.3897,
      "SEM花费(SPD)": 1125.58,
      "SEM ROI": 2.17,
      "SEM CPC": 7.1693
    },
    {
      "账户": "GMEC-Downy",
      "SKU名称": "当妮护衣留香珠组套200g*3瓶(自由之森+玫瑰之巅+清雨山茶)",
      "SKU简称": "当妮留香珠200g*3",
      "SKU ID": "100111047759",
      "综合ROI(含JST+SEM)": 0.63,
      "综合花费(SPD)": 291.75,
      "综合CPC": 4.0,
      "综合CTR": 0.0282,
      "综合CVR": 0.0274,
      "状态": "🔻 低于目标10%以上",
      "ROI目标": 3.0,
      "JST花费(SPD)": 203.36,
      "JST ROI": 0.91,
      "JST CPC": 4.3268,
      "SEM花费(SPD)": 88.39,
      "SEM ROI": 0.0,
      "SEM CPC": 3.3996
    },
    {
      "账户": "GMEC-Downy",
      "SKU名称": "当妮护衣留香珠自由之森450g 12周持久留香防异味 99%除菌除螨 易溶解",
      "SKU简称": "当妮450g自由之森",
      "SKU ID": "100053319577",
      "综合ROI(含JST+SEM)": 1.71,
      "综合花费(SPD)": 2093.34,
      "综合CPC": 6.02,
      "综合CTR": 0.0649,
      "综合CVR": 0.1494,
      "状态": "🔻 低于目标10%以上",
      "ROI目标": 3.0,
      "JST花费(SPD)": 569.37,
      "JST ROI": 1.48,
      "JST CPC": 5.6373,
      "SEM花费(SPD)": 1523.97,
      "SEM ROI": 1.8,
      "SEM CPC": 6.1699
    },
    {
      "账户": "GMEC-Downy",
      "SKU名称": "当妮护衣留香珠自由之森950g 12周持久留香 防异味 99%除菌除螨家庭装",
      "SKU简称": "当妮950g自由之森",
      "SKU ID": "100301903542",
      "综合ROI(含JST+SEM)": 1.61,
      "综合花费(SPD)": 1077.21,
      "综合CPC": 9.7,
      "综合CTR": 0.0426,
      "综合CVR": 0.1712,
      "状态": "🔻 低于目标10%以上",
      "ROI目标": 3.0,
      "JST花费(SPD)": 138.01,
      "JST ROI": 2.13,
      "JST CPC": 4.3128,
      "SEM花费(SPD)": 939.2,
      "SEM ROI": 1.53,
      "SEM CPC": 11.8886
    },
    {
      "账户": "GMEC-Tide",
      "SKU名称": "汰渍洗衣免搓粉 清雅山茶花6.8斤装 洗衣粉非爆炸盐皂粉 持久留香30天",
      "SKU简称": "汰渍山茶花3.4kg",
      "SKU ID": "100161974102",
      "综合ROI(含JST+SEM)": 1.91,
      "综合花费(SPD)": 4070.04,
      "综合CPC": 6.96,
      "综合CTR": 0.0378,
      "综合CVR": 0.2393,
      "状态": "🔺 高于目标10%以上",
      "ROI目标": 1.5,
      "JST花费(SPD)": 703.04,
      "JST ROI": 2.25,
      "JST CPC": 3.6239,
      "SEM花费(SPD)": 3367.0,
      "SEM ROI": 1.83,
      "SEM CPC": 8.6113
    },
    {
      "账户": "GMEC-Tide",
      "SKU名称": "汰渍洗衣免搓粉 阳光薰衣草6.8斤装 洗衣粉非爆炸盐皂粉 持久留香30天",
      "SKU简称": "汰渍薰衣草3.4kg",
      "SKU ID": "100131766577",
      "综合ROI(含JST+SEM)": 1.05,
      "综合花费(SPD)": 1708.66,
      "综合CPC": 12.47,
      "综合CTR": 0.0527,
      "综合CVR": 0.2628,
      "状态": "🔻 低于目标10%以上",
      "ROI目标": 1.5,
      "JST花费(SPD)": 17.12,
      "JST ROI": 0.0,
      "JST CPC": 2.4457,
      "SEM花费(SPD)": 1691.54,
      "SEM ROI": 1.06,
      "SEM CPC": 13.0118
    },
    {
      "账户": "GMEC-Tide-L",
      "SKU名称": "汰渍去渍洗衣液洁雅百合16斤瓶装(2kg*4)家庭装 无惧混洗  支持快洗",
      "SKU简称": "汰渍百合16斤",
      "SKU ID": "100008794192",
      "综合ROI(含JST+SEM)": 2.13,
      "综合花费(SPD)": 742.52,
      "综合CPC": 7.14,
      "综合CTR": 0.0415,
      "综合CVR": 0.125,
      "状态": "🔻 低于目标10%以上",
      "ROI目标": 2.5,
      "JST花费(SPD)": 55.0,
      "JST ROI": 3.63,
      "JST CPC": 2.75,
      "SEM花费(SPD)": 687.52,
      "SEM ROI": 2.01,
      "SEM CPC": 8.1848
    },
    {
      "账户": "GMEC-Tide-L",
      "SKU名称": "汰渍去渍洗衣液洁雅百合18斤装(3kg*2瓶+500g*6袋)家庭装 无惧混洗",
      "SKU简称": "汰渍9kg",
      "SKU ID": "2795972",
      "综合ROI(含JST+SEM)": 1.99,
      "综合花费(SPD)": 1574.07,
      "综合CPC": 9.1,
      "综合CTR": 0.0468,
      "综合CVR": 0.1734,
      "状态": "🔻 低于目标10%以上",
      "ROI目标": 2.5,
      "JST花费(SPD)": 65.17,
      "JST ROI": 5.29,
      "JST CPC": 3.8335,
      "SEM花费(SPD)": 1508.9,
      "SEM ROI": 1.85,
      "SEM CPC": 9.6724
    },
    {
      "账户": "GMEC-Tide-L",
      "SKU名称": "汰渍去渍洗衣液洁雅百合24斤瓶装(3kg*4)家庭装 无惧混洗  支持快洗",
      "SKU简称": "汰渍百合24斤",
      "SKU ID": "2646498",
      "综合ROI(含JST+SEM)": 2.6,
      "综合花费(SPD)": 5034.38,
      "综合CPC": 14.47,
      "综合CTR": 0.0471,
      "综合CVR": 0.2586,
      "状态": "正常",
      "ROI目标": 2.5,
      "JST花费(SPD)": 64.79,
      "JST ROI": 13.02,
      "JST CPC": 3.2395,
      "SEM花费(SPD)": 4969.59,
      "SEM ROI": 2.46,
      "SEM CPC": 15.1512
    },
    {
      "账户": "GMEC-Tide-L",
      "SKU名称": "汰渍去渍洗衣液淡雅樱花11斤瓶装(2.75kg×2)家庭装 无惧混洗",
      "SKU简称": "汰渍SAK5.5kg",
      "SKU ID": "100063120723",
      "综合ROI(含JST+SEM)": 2.15,
      "综合花费(SPD)": 1104.7,
      "综合CPC": 9.36,
      "综合CTR": 0.0375,
      "综合CVR": 0.2373,
      "状态": "🔻 低于目标10%以上",
      "ROI目标": 2.5,
      "JST花费(SPD)": 213.86,
      "JST ROI": 4.19,
      "JST CPC": 4.8605,
      "SEM花费(SPD)": 890.84,
      "SEM ROI": 1.65,
      "SEM CPC": 12.0384
    },
    {
      "账户": "GMEC-Tide-L",
      "SKU名称": "汰渍去渍洗衣液淡雅薰香11斤装(2kg*2瓶+500g*3袋)家庭装 无惧混洗",
      "SKU简称": "汰渍LAV5.5kg",
      "SKU ID": "100063120717",
      "综合ROI(含JST+SEM)": 1.06,
      "综合花费(SPD)": 263.11,
      "综合CPC": 3.56,
      "综合CTR": 0.0494,
      "综合CVR": 0.0541,
      "状态": "🔻 低于目标10%以上",
      "ROI目标": 2.5,
      "JST花费(SPD)": 84.42,
      "JST ROI": 2.56,
      "JST CPC": 1.9633,
      "SEM花费(SPD)": 178.69,
      "SEM ROI": 0.36,
      "SEM CPC": 5.7642
    }
  ],
  "ht": [
    {
      "账户": "GMEC-Ariel",
      "HT花费(SPD)": 1877.18,
      "HT ROI": 2.01
    },
    {
      "账户": "GMEC-Ariel-L",
      "HT花费(SPD)": 5834.24,
      "HT ROI": 2.49
    },
    {
      "账户": "GMEC-Downy",
      "HT花费(SPD)": 6326.59,
      "HT ROI": 2.25
    },
    {
      "账户": "GMEC-Tide",
      "HT花费(SPD)": 1670.16,
      "HT ROI": 2.01
    },
    {
      "账户": "GMEC-Tide-L",
      "HT花费(SPD)": 4785.53,
      "HT ROI": 2.19
    }
  ],
  "deltas": {
    "total_spend": {
      "vs_2h": {
        "diff": 11653.41,
        "pct": 22.5,
        "index_pct": 122.5,
        "direction": "up"
      },
      "vs_yesterday": {
        "diff": 19970.94,
        "pct": 45.93,
        "index_pct": 145.93,
        "direction": "up"
      }
    },
    "total_roi": {
      "vs_2h": {
        "diff": -0.15,
        "pct": -6.61,
        "index_pct": 93.39,
        "direction": "down"
      },
      "vs_yesterday": {
        "diff": -0.13,
        "pct": -5.8,
        "index_pct": 94.2,
        "direction": "down"
      }
    },
    "accounts": {
      "GMEC-Ariel": {
        "综合花费": {
          "vs_2h": {
            "diff": 1676.76,
            "pct": 19.99,
            "index_pct": 119.99,
            "direction": "up"
          },
          "vs_yesterday": {
            "diff": 3477.7,
            "pct": 52.79,
            "index_pct": 152.79,
            "direction": "up"
          }
        },
        "综合ROI": {
          "vs_2h": {
            "diff": -0.14,
            "pct": -7.02,
            "index_pct": 92.98,
            "direction": "down"
          },
          "vs_yesterday": {
            "diff": -0.28,
            "pct": -13.49,
            "index_pct": 86.51,
            "direction": "down"
          }
        }
      },
      "GMEC-Ariel-L": {
        "综合花费": {
          "vs_2h": {
            "diff": 4175.23,
            "pct": 27.32,
            "index_pct": 127.32,
            "direction": "up"
          },
          "vs_yesterday": {
            "diff": 10091.74,
            "pct": 107.77,
            "index_pct": 207.77,
            "direction": "up"
          }
        },
        "综合ROI": {
          "vs_2h": {
            "diff": -0.33,
            "pct": -12.47,
            "index_pct": 87.53,
            "direction": "down"
          },
          "vs_yesterday": {
            "diff": -0.5,
            "pct": -18.05,
            "index_pct": 81.95,
            "direction": "down"
          }
        }
      },
      "GMEC-Downy": {
        "综合花费": {
          "vs_2h": {
            "diff": 2120.05,
            "pct": 19.53,
            "index_pct": 119.53,
            "direction": "up"
          },
          "vs_yesterday": {
            "diff": 1850.8,
            "pct": 16.63,
            "index_pct": 116.63,
            "direction": "up"
          }
        },
        "综合ROI": {
          "vs_2h": {
            "diff": -0.09,
            "pct": -3.88,
            "index_pct": 96.12,
            "direction": "down"
          },
          "vs_yesterday": {
            "diff": 0.38,
            "pct": 20.76,
            "index_pct": 120.76,
            "direction": "up"
          }
        }
      },
      "GMEC-Tide": {
        "综合花费": {
          "vs_2h": {
            "diff": 1411.82,
            "pct": 23.39,
            "index_pct": 123.39,
            "direction": "up"
          },
          "vs_yesterday": {
            "diff": 973.82,
            "pct": 15.04,
            "index_pct": 115.04,
            "direction": "up"
          }
        },
        "综合ROI": {
          "vs_2h": {
            "diff": 0.01,
            "pct": 0.8,
            "index_pct": 100.8,
            "direction": "up"
          },
          "vs_yesterday": {
            "diff": -0.01,
            "pct": -0.77,
            "index_pct": 99.23,
            "direction": "down"
          }
        }
      },
      "GMEC-Tide-L": {
        "综合花费": {
          "vs_2h": {
            "diff": 2269.55,
            "pct": 20.2,
            "index_pct": 120.2,
            "direction": "up"
          },
          "vs_yesterday": {
            "diff": 3576.88,
            "pct": 36.03,
            "index_pct": 136.03,
            "direction": "up"
          }
        },
        "综合ROI": {
          "vs_2h": {
            "diff": -0.08,
            "pct": -3.28,
            "index_pct": 96.72,
            "direction": "down"
          },
          "vs_yesterday": {
            "diff": -0.41,
            "pct": -15.1,
            "index_pct": 84.9,
            "direction": "down"
          }
        }
      }
    },
    "skus": [
      {
        "账户": "GMEC-Ariel",
        "SKU ID": "100161952438",
        "综合花费": {
          "vs_2h": {
            "diff": 1101.7,
            "pct": 17.79,
            "index_pct": 117.79,
            "direction": "up"
          },
          "vs_yesterday": {
            "diff": 2553.84,
            "pct": 53.88,
            "index_pct": 153.88,
            "direction": "up"
          }
        },
        "综合ROI": {
          "vs_2h": {
            "diff": -0.14,
            "pct": -7.41,
            "index_pct": 92.59,
            "direction": "down"
          },
          "vs_yesterday": {
            "diff": -0.3,
            "pct": -14.63,
            "index_pct": 85.37,
            "direction": "down"
          }
        },
        "JST花费": {
          "vs_2h": {
            "diff": 27.56,
            "pct": 3.71,
            "index_pct": 103.71,
            "direction": "up"
          },
          "vs_yesterday": {
            "diff": 123.03,
            "pct": 19.01,
            "index_pct": 119.01,
            "direction": "up"
          }
        },
        "JST ROI": {
          "vs_2h": {
            "diff": -0.09,
            "pct": -3.66,
            "index_pct": 96.34,
            "direction": "down"
          },
          "vs_yesterday": {
            "diff": -0.34,
            "pct": -12.55,
            "index_pct": 87.45,
            "direction": "down"
          }
        },
        "SEM花费": {
          "vs_2h": {
            "diff": 1074.14,
            "pct": 19.71,
            "index_pct": 119.71,
            "direction": "up"
          },
          "vs_yesterday": {
            "diff": 2430.81,
            "pct": 59.39,
            "index_pct": 159.39,
            "direction": "up"
          }
        },
        "SEM ROI": {
          "vs_2h": {
            "diff": -0.13,
            "pct": -7.18,
            "index_pct": 92.82,
            "direction": "down"
          },
          "vs_yesterday": {
            "diff": -0.27,
            "pct": -13.85,
            "index_pct": 86.15,
            "direction": "down"
          }
        }
      },
      {
        "账户": "GMEC-Ariel",
        "SKU ID": "100162871390",
        "综合花费": {
          "vs_2h": {
            "diff": 19.29,
            "pct": 2.21,
            "index_pct": 102.21,
            "direction": "up"
          },
          "vs_yesterday": {
            "diff": 210.48,
            "pct": 30.79,
            "index_pct": 130.79,
            "direction": "up"
          }
        },
        "综合ROI": {
          "vs_2h": {
            "diff": 0.13,
            "pct": 7.22,
            "index_pct": 107.22,
            "direction": "up"
          },
          "vs_yesterday": {
            "diff": 0.24,
            "pct": 14.2,
            "index_pct": 114.2,
            "direction": "up"
          }
        },
        "JST花费": {
          "vs_2h": {
            "diff": 11.98,
            "pct": 9.02,
            "index_pct": 109.02,
            "direction": "up"
          },
          "vs_yesterday": {
            "diff": 36.33,
            "pct": 33.48,
            "index_pct": 133.48,
            "direction": "up"
          }
        },
        "JST ROI": {
          "vs_2h": {
            "diff": 0.06,
            "pct": 1.71,
            "index_pct": 101.71,
            "direction": "up"
          },
          "vs_yesterday": {
            "diff": 1.12,
            "pct": 45.9,
            "index_pct": 145.9,
            "direction": "up"
          }
        },
        "SEM花费": {
          "vs_2h": {
            "diff": 7.31,
            "pct": 0.99,
            "index_pct": 100.99,
            "direction": "up"
          },
          "vs_yesterday": {
            "diff": 174.15,
            "pct": 30.29,
            "index_pct": 130.29,
            "direction": "up"
          }
        },
        "SEM ROI": {
          "vs_2h": {
            "diff": 0.12,
            "pct": 8.05,
            "index_pct": 108.05,
            "direction": "up"
          },
          "vs_yesterday": {
            "diff": 0.06,
            "pct": 3.87,
            "index_pct": 103.87,
            "direction": "up"
          }
        }
      },
      {
        "账户": "GMEC-Ariel-L",
        "SKU ID": "100036714440",
        "综合花费": {
          "vs_2h": {
            "diff": 1785.56,
            "pct": 46.02,
            "index_pct": 146.02,
            "direction": "up"
          },
          "vs_yesterday": {
            "diff": 4311.35,
            "pct": 318.29,
            "index_pct": 418.29,
            "direction": "up"
          }
        },
        "综合ROI": {
          "vs_2h": {
            "diff": -0.54,
            "pct": -18.06,
            "index_pct": 81.94,
            "direction": "down"
          },
          "vs_yesterday": {
            "diff": 0.21,
            "pct": 9.37,
            "index_pct": 109.38,
            "direction": "up"
          }
        },
        "JST花费": {
          "vs_2h": {
            "diff": 0.0,
            "pct": 0.0,
            "index_pct": 100.0,
            "direction": "neutral"
          },
          "vs_yesterday": {
            "diff": 9.21,
            "pct": 16.75,
            "index_pct": 116.75,
            "direction": "up"
          }
        },
        "JST ROI": {
          "vs_2h": {
            "diff": 0.0,
            "pct": 0.0,
            "index_pct": 100.0,
            "direction": "neutral"
          },
          "vs_yesterday": {
            "diff": 12.99,
            "pct": 319.16,
            "index_pct": 419.16,
            "direction": "up"
          }
        },
        "SEM花费": {
          "vs_2h": {
            "diff": 1785.56,
            "pct": 46.79,
            "index_pct": 146.79,
            "direction": "up"
          },
          "vs_yesterday": {
            "diff": 4302.14,
            "pct": 331.05,
            "index_pct": 431.05,
            "direction": "up"
          }
        },
        "SEM ROI": {
          "vs_2h": {
            "diff": -0.46,
            "pct": -16.73,
            "index_pct": 83.27,
            "direction": "down"
          },
          "vs_yesterday": {
            "diff": 0.13,
            "pct": 6.02,
            "index_pct": 106.02,
            "direction": "up"
          }
        }
      },
      {
        "账户": "GMEC-Ariel-L",
        "SKU ID": "4713934",
        "综合花费": {
          "vs_2h": {
            "diff": 126.61,
            "pct": 27.52,
            "index_pct": 127.52,
            "direction": "up"
          },
          "vs_yesterday": {
            "diff": 307.74,
            "pct": 110.31,
            "index_pct": 210.31,
            "direction": "up"
          }
        },
        "综合ROI": {
          "vs_2h": {
            "diff": -1.06,
            "pct": -18.96,
            "index_pct": 81.04,
            "direction": "down"
          },
          "vs_yesterday": {
            "diff": -3.23,
            "pct": -41.62,
            "index_pct": 58.38,
            "direction": "down"
          }
        },
        "JST花费": {
          "vs_2h": {
            "diff": 0.0,
            "pct": 0.0,
            "index_pct": 100.0,
            "direction": "neutral"
          },
          "vs_yesterday": {
            "diff": -0.44,
            "pct": -0.33,
            "index_pct": 99.67,
            "direction": "down"
          }
        },
        "JST ROI": {
          "vs_2h": {
            "diff": 0.0,
            "pct": 0.0,
            "index_pct": 100.0,
            "direction": "neutral"
          },
          "vs_yesterday": {
            "diff": 0.55,
            "pct": 3.43,
            "index_pct": 103.43,
            "direction": "up"
          }
        },
        "SEM花费": {
          "vs_2h": {
            "diff": 126.61,
            "pct": 38.9,
            "index_pct": 138.9,
            "direction": "up"
          },
          "vs_yesterday": {
            "diff": 308.18,
            "pct": 214.21,
            "index_pct": 314.21,
            "direction": "up"
          }
        },
        "SEM ROI": {
          "vs_2h": {
            "diff": -0.1,
            "pct": -9.62,
            "index_pct": 90.38,
            "direction": "down"
          },
          "vs_yesterday": {
            "diff": 0,
            "pct": 0,
            "index_pct": 0,
            "direction": "neutral"
          }
        }
      },
      {
        "账户": "GMEC-Ariel-L",
        "SKU ID": "100039735595",
        "综合花费": {
          "vs_2h": {
            "diff": 33.44,
            "pct": 4.61,
            "index_pct": 104.61,
            "direction": "up"
          },
          "vs_yesterday": {
            "diff": 554.74,
            "pct": 271.29,
            "index_pct": 371.29,
            "direction": "up"
          }
        },
        "综合ROI": {
          "vs_2h": {
            "diff": 0.07,
            "pct": 3.89,
            "index_pct": 103.89,
            "direction": "up"
          },
          "vs_yesterday": {
            "diff": -0.28,
            "pct": -13.02,
            "index_pct": 86.98,
            "direction": "down"
          }
        },
        "JST花费": {
          "vs_2h": {
            "diff": 0.0,
            "pct": 0.0,
            "index_pct": 100.0,
            "direction": "neutral"
          },
          "vs_yesterday": {
            "diff": 0.11,
            "pct": 0.21,
            "index_pct": 100.21,
            "direction": "up"
          }
        },
        "JST ROI": {
          "vs_2h": {
            "diff": 0.0,
            "pct": 0.0,
            "index_pct": 100.0,
            "direction": "neutral"
          },
          "vs_yesterday": {
            "diff": 4.0,
            "pct": 194.17,
            "index_pct": 294.17,
            "direction": "up"
          }
        },
        "SEM花费": {
          "vs_2h": {
            "diff": 33.44,
            "pct": 4.97,
            "index_pct": 104.97,
            "direction": "up"
          },
          "vs_yesterday": {
            "diff": 554.63,
            "pct": 367.23,
            "index_pct": 467.23,
            "direction": "up"
          }
        },
        "SEM ROI": {
          "vs_2h": {
            "diff": 0.09,
            "pct": 6.16,
            "index_pct": 106.16,
            "direction": "up"
          },
          "vs_yesterday": {
            "diff": -0.63,
            "pct": -28.9,
            "index_pct": 71.1,
            "direction": "down"
          }
        }
      },
      {
        "账户": "GMEC-Ariel-L",
        "SKU ID": "1978117",
        "综合花费": {
          "vs_2h": {
            "diff": 351.43,
            "pct": 10.97,
            "index_pct": 110.97,
            "direction": "up"
          },
          "vs_yesterday": {
            "diff": 1921.75,
            "pct": 117.75,
            "index_pct": 217.75,
            "direction": "up"
          }
        },
        "综合ROI": {
          "vs_2h": {
            "diff": -0.1,
            "pct": -4.72,
            "index_pct": 95.28,
            "direction": "down"
          },
          "vs_yesterday": {
            "diff": -1.06,
            "pct": -34.42,
            "index_pct": 65.58,
            "direction": "down"
          }
        },
        "JST花费": {
          "vs_2h": {
            "diff": 0.0,
            "pct": 0.0,
            "index_pct": 100.0,
            "direction": "neutral"
          },
          "vs_yesterday": {
            "diff": -0.59,
            "pct": -0.48,
            "index_pct": 99.52,
            "direction": "down"
          }
        },
        "JST ROI": {
          "vs_2h": {
            "diff": 0.0,
            "pct": 0.0,
            "index_pct": 100.0,
            "direction": "neutral"
          },
          "vs_yesterday": {
            "diff": 0.95,
            "pct": 9.95,
            "index_pct": 109.95,
            "direction": "up"
          }
        },
        "SEM花费": {
          "vs_2h": {
            "diff": 351.43,
            "pct": 11.41,
            "index_pct": 111.41,
            "direction": "up"
          },
          "vs_yesterday": {
            "diff": 1922.34,
            "pct": 127.36,
            "index_pct": 227.36,
            "direction": "up"
          }
        },
        "SEM ROI": {
          "vs_2h": {
            "diff": -0.07,
            "pct": -3.91,
            "index_pct": 96.09,
            "direction": "down"
          },
          "vs_yesterday": {
            "diff": -0.83,
            "pct": -32.55,
            "index_pct": 67.45,
            "direction": "down"
          }
        }
      },
      {
        "账户": "GMEC-Ariel-L",
        "SKU ID": "100008766160",
        "综合花费": {
          "vs_2h": {
            "diff": 211.19,
            "pct": 14.72,
            "index_pct": 114.72,
            "direction": "up"
          },
          "vs_yesterday": {
            "diff": 0,
            "pct": 0,
            "index_pct": 0,
            "direction": "neutral"
          }
        },
        "综合ROI": {
          "vs_2h": {
            "diff": -0.13,
            "pct": -8.28,
            "index_pct": 91.72,
            "direction": "down"
          },
          "vs_yesterday": {
            "diff": 0,
            "pct": 0,
            "index_pct": 0,
            "direction": "neutral"
          }
        },
        "JST花费": {
          "vs_2h": {
            "diff": 0.0,
            "pct": 0.0,
            "index_pct": 100.0,
            "direction": "neutral"
          },
          "vs_yesterday": {
            "diff": 0,
            "pct": 0,
            "index_pct": 0,
            "direction": "neutral"
          }
        },
        "JST ROI": {
          "vs_2h": {
            "diff": 0.0,
            "pct": 0.0,
            "index_pct": 100.0,
            "direction": "neutral"
          },
          "vs_yesterday": {
            "diff": 0,
            "pct": 0,
            "index_pct": 0,
            "direction": "neutral"
          }
        },
        "SEM花费": {
          "vs_2h": {
            "diff": 211.19,
            "pct": 15.41,
            "index_pct": 115.41,
            "direction": "up"
          },
          "vs_yesterday": {
            "diff": 0,
            "pct": 0,
            "index_pct": 0,
            "direction": "neutral"
          }
        },
        "SEM ROI": {
          "vs_2h": {
            "diff": -0.1,
            "pct": -7.81,
            "index_pct": 92.19,
            "direction": "down"
          },
          "vs_yesterday": {
            "diff": 0,
            "pct": 0,
            "index_pct": 0,
            "direction": "neutral"
          }
        }
      },
      {
        "账户": "GMEC-Ariel-L",
        "SKU ID": "100006804447",
        "综合花费": {
          "vs_2h": {
            "diff": 623.45,
            "pct": 79.25,
            "index_pct": 179.25,
            "direction": "up"
          },
          "vs_yesterday": {
            "diff": 594.87,
            "pct": 72.97,
            "index_pct": 172.97,
            "direction": "up"
          }
        },
        "综合ROI": {
          "vs_2h": {
            "diff": -1.29,
            "pct": -42.02,
            "index_pct": 57.98,
            "direction": "down"
          },
          "vs_yesterday": {
            "diff": -1.28,
            "pct": -41.83,
            "index_pct": 58.17,
            "direction": "down"
          }
        },
        "JST花费": {
          "vs_2h": {
            "diff": 0.0,
            "pct": 0.0,
            "index_pct": 100.0,
            "direction": "neutral"
          },
          "vs_yesterday": {
            "diff": -0.66,
            "pct": -0.56,
            "index_pct": 99.44,
            "direction": "down"
          }
        },
        "JST ROI": {
          "vs_2h": {
            "diff": 0.0,
            "pct": 0.0,
            "index_pct": 100.0,
            "direction": "neutral"
          },
          "vs_yesterday": {
            "diff": 1.16,
            "pct": 10.92,
            "index_pct": 110.92,
            "direction": "up"
          }
        },
        "SEM花费": {
          "vs_2h": {
            "diff": 623.45,
            "pct": 93.21,
            "index_pct": 193.21,
            "direction": "up"
          },
          "vs_yesterday": {
            "diff": 595.53,
            "pct": 85.47,
            "index_pct": 185.47,
            "direction": "up"
          }
        },
        "SEM ROI": {
          "vs_2h": {
            "diff": -0.67,
            "pct": -43.51,
            "index_pct": 56.49,
            "direction": "down"
          },
          "vs_yesterday": {
            "diff": -0.91,
            "pct": -51.12,
            "index_pct": 48.88,
            "direction": "down"
          }
        }
      },
      {
        "账户": "GMEC-Downy",
        "SKU ID": "100268112394",
        "综合花费": {
          "vs_2h": {
            "diff": 0.0,
            "pct": 0.0,
            "index_pct": 100.0,
            "direction": "neutral"
          },
          "vs_yesterday": {
            "diff": -115.52,
            "pct": -58.08,
            "index_pct": 41.92,
            "direction": "down"
          }
        },
        "综合ROI": {
          "vs_2h": {
            "diff": 0.0,
            "pct": 0.0,
            "index_pct": 100.0,
            "direction": "neutral"
          },
          "vs_yesterday": {
            "diff": 0,
            "pct": 0,
            "index_pct": 0,
            "direction": "neutral"
          }
        },
        "JST花费": {
          "vs_2h": {
            "diff": 0.0,
            "pct": 0.0,
            "index_pct": 100.0,
            "direction": "neutral"
          },
          "vs_yesterday": {
            "diff": 82.75,
            "pct": 13346.77,
            "index_pct": 13446.77,
            "direction": "up"
          }
        },
        "JST ROI": {
          "vs_2h": {
            "diff": 0.0,
            "pct": 0.0,
            "index_pct": 100.0,
            "direction": "neutral"
          },
          "vs_yesterday": {
            "diff": 0,
            "pct": 0,
            "index_pct": 0,
            "direction": "neutral"
          }
        },
        "SEM花费": {
          "vs_2h": {
            "diff": 0,
            "pct": 0,
            "index_pct": 0,
            "direction": "neutral"
          },
          "vs_yesterday": {
            "diff": -198.27,
            "pct": -100.0,
            "index_pct": 0.0,
            "direction": "down"
          }
        },
        "SEM ROI": {
          "vs_2h": {
            "diff": 0,
            "pct": 0,
            "index_pct": 0,
            "direction": "neutral"
          },
          "vs_yesterday": {
            "diff": 0,
            "pct": 0,
            "index_pct": 0,
            "direction": "neutral"
          }
        }
      },
      {
        "账户": "GMEC-Downy",
        "SKU ID": "100233530169",
        "综合花费": {
          "vs_2h": {
            "diff": 22.03,
            "pct": 7.72,
            "index_pct": 107.72,
            "direction": "up"
          },
          "vs_yesterday": {
            "diff": 244.54,
            "pct": 388.47,
            "index_pct": 488.47,
            "direction": "up"
          }
        },
        "综合ROI": {
          "vs_2h": {
            "diff": -0.22,
            "pct": -7.38,
            "index_pct": 92.62,
            "direction": "down"
          },
          "vs_yesterday": {
            "diff": 0,
            "pct": 0,
            "index_pct": 0,
            "direction": "neutral"
          }
        },
        "JST花费": {
          "vs_2h": {
            "diff": 0.0,
            "pct": 0.0,
            "index_pct": 100.0,
            "direction": "neutral"
          },
          "vs_yesterday": {
            "diff": 3.27,
            "pct": 1308.0,
            "index_pct": 1408.0,
            "direction": "up"
          }
        },
        "JST ROI": {
          "vs_2h": {
            "diff": 0,
            "pct": 0,
            "index_pct": 0,
            "direction": "neutral"
          },
          "vs_yesterday": {
            "diff": 0,
            "pct": 0,
            "index_pct": 0,
            "direction": "neutral"
          }
        },
        "SEM花费": {
          "vs_2h": {
            "diff": 22.03,
            "pct": 7.81,
            "index_pct": 107.81,
            "direction": "up"
          },
          "vs_yesterday": {
            "diff": 241.27,
            "pct": 384.8,
            "index_pct": 484.8,
            "direction": "up"
          }
        },
        "SEM ROI": {
          "vs_2h": {
            "diff": -0.22,
            "pct": -7.31,
            "index_pct": 92.69,
            "direction": "down"
          },
          "vs_yesterday": {
            "diff": 0,
            "pct": 0,
            "index_pct": 0,
            "direction": "neutral"
          }
        }
      },
      {
        "账户": "GMEC-Downy",
        "SKU ID": "100094637928",
        "综合花费": {
          "vs_2h": {
            "diff": 0.0,
            "pct": 0.0,
            "index_pct": 100.0,
            "direction": "neutral"
          },
          "vs_yesterday": {
            "diff": 419.54,
            "pct": 296.87,
            "index_pct": 396.87,
            "direction": "up"
          }
        },
        "综合ROI": {
          "vs_2h": {
            "diff": 0.0,
            "pct": 0.0,
            "index_pct": 100.0,
            "direction": "neutral"
          },
          "vs_yesterday": {
            "diff": -0.49,
            "pct": -20.42,
            "index_pct": 79.58,
            "direction": "down"
          }
        },
        "JST花费": {
          "vs_2h": {
            "diff": 0.0,
            "pct": 0.0,
            "index_pct": 100.0,
            "direction": "neutral"
          },
          "vs_yesterday": {
            "diff": 406.18,
            "pct": 341.47,
            "index_pct": 441.47,
            "direction": "up"
          }
        },
        "JST ROI": {
          "vs_2h": {
            "diff": 0.0,
            "pct": 0.0,
            "index_pct": 100.0,
            "direction": "neutral"
          },
          "vs_yesterday": {
            "diff": -0.94,
            "pct": -32.98,
            "index_pct": 67.02,
            "direction": "down"
          }
        },
        "SEM花费": {
          "vs_2h": {
            "diff": 0.0,
            "pct": 0.0,
            "index_pct": 100.0,
            "direction": "neutral"
          },
          "vs_yesterday": {
            "diff": 13.36,
            "pct": 59.72,
            "index_pct": 159.72,
            "direction": "up"
          }
        },
        "SEM ROI": {
          "vs_2h": {
            "diff": 0.0,
            "pct": 0.0,
            "index_pct": 100.0,
            "direction": "neutral"
          },
          "vs_yesterday": {
            "diff": 0,
            "pct": 0,
            "index_pct": 0,
            "direction": "neutral"
          }
        }
      },
      {
        "账户": "GMEC-Downy",
        "SKU ID": "100044243858",
        "综合花费": {
          "vs_2h": {
            "diff": 429.15,
            "pct": 23.75,
            "index_pct": 123.75,
            "direction": "up"
          },
          "vs_yesterday": {
            "diff": -984.46,
            "pct": -30.57,
            "index_pct": 69.43,
            "direction": "down"
          }
        },
        "综合ROI": {
          "vs_2h": {
            "diff": -0.21,
            "pct": -6.58,
            "index_pct": 93.42,
            "direction": "down"
          },
          "vs_yesterday": {
            "diff": 1.21,
            "pct": 68.36,
            "index_pct": 168.36,
            "direction": "up"
          }
        },
        "JST花费": {
          "vs_2h": {
            "diff": 17.38,
            "pct": 1.59,
            "index_pct": 101.59,
            "direction": "up"
          },
          "vs_yesterday": {
            "diff": 44.0,
            "pct": 4.13,
            "index_pct": 104.13,
            "direction": "up"
          }
        },
        "JST ROI": {
          "vs_2h": {
            "diff": 0.13,
            "pct": 3.53,
            "index_pct": 103.53,
            "direction": "up"
          },
          "vs_yesterday": {
            "diff": 1.81,
            "pct": 90.5,
            "index_pct": 190.5,
            "direction": "up"
          }
        },
        "SEM花费": {
          "vs_2h": {
            "diff": 411.77,
            "pct": 57.69,
            "index_pct": 157.69,
            "direction": "up"
          },
          "vs_yesterday": {
            "diff": -1028.46,
            "pct": -47.75,
            "index_pct": 52.25,
            "direction": "down"
          }
        },
        "SEM ROI": {
          "vs_2h": {
            "diff": -0.26,
            "pct": -10.7,
            "index_pct": 89.3,
            "direction": "down"
          },
          "vs_yesterday": {
            "diff": 0.52,
            "pct": 31.52,
            "index_pct": 131.52,
            "direction": "up"
          }
        }
      },
      {
        "账户": "GMEC-Downy",
        "SKU ID": "100111047759",
        "综合花费": {
          "vs_2h": {
            "diff": 0.1,
            "pct": 0.03,
            "index_pct": 100.03,
            "direction": "up"
          },
          "vs_yesterday": {
            "diff": -283.24,
            "pct": -49.26,
            "index_pct": 50.74,
            "direction": "down"
          }
        },
        "综合ROI": {
          "vs_2h": {
            "diff": 0.0,
            "pct": 0.0,
            "index_pct": 100.0,
            "direction": "neutral"
          },
          "vs_yesterday": {
            "diff": -0.71,
            "pct": -52.99,
            "index_pct": 47.01,
            "direction": "down"
          }
        },
        "JST花费": {
          "vs_2h": {
            "diff": 0.1,
            "pct": 0.05,
            "index_pct": 100.05,
            "direction": "up"
          },
          "vs_yesterday": {
            "diff": -45.33,
            "pct": -18.23,
            "index_pct": 81.77,
            "direction": "down"
          }
        },
        "JST ROI": {
          "vs_2h": {
            "diff": 0.0,
            "pct": 0.0,
            "index_pct": 100.0,
            "direction": "neutral"
          },
          "vs_yesterday": {
            "diff": 0.22,
            "pct": 31.88,
            "index_pct": 131.88,
            "direction": "up"
          }
        },
        "SEM花费": {
          "vs_2h": {
            "diff": 0.0,
            "pct": 0.0,
            "index_pct": 100.0,
            "direction": "neutral"
          },
          "vs_yesterday": {
            "diff": -237.91,
            "pct": -72.91,
            "index_pct": 27.09,
            "direction": "down"
          }
        },
        "SEM ROI": {
          "vs_2h": {
            "diff": 0,
            "pct": 0,
            "index_pct": 0,
            "direction": "neutral"
          },
          "vs_yesterday": {
            "diff": -1.84,
            "pct": -100.0,
            "index_pct": 0.0,
            "direction": "down"
          }
        }
      },
      {
        "账户": "GMEC-Downy",
        "SKU ID": "100053319577",
        "综合花费": {
          "vs_2h": {
            "diff": 299.02,
            "pct": 16.66,
            "index_pct": 116.66,
            "direction": "up"
          },
          "vs_yesterday": {
            "diff": 945.77,
            "pct": 82.42,
            "index_pct": 182.42,
            "direction": "up"
          }
        },
        "综合ROI": {
          "vs_2h": {
            "diff": -0.18,
            "pct": -9.52,
            "index_pct": 90.48,
            "direction": "down"
          },
          "vs_yesterday": {
            "diff": -0.37,
            "pct": -17.79,
            "index_pct": 82.21,
            "direction": "down"
          }
        },
        "JST花费": {
          "vs_2h": {
            "diff": 26.53,
            "pct": 4.89,
            "index_pct": 104.89,
            "direction": "up"
          },
          "vs_yesterday": {
            "diff": 7.93,
            "pct": 1.41,
            "index_pct": 101.41,
            "direction": "up"
          }
        },
        "JST ROI": {
          "vs_2h": {
            "diff": -0.07,
            "pct": -4.52,
            "index_pct": 95.48,
            "direction": "down"
          },
          "vs_yesterday": {
            "diff": -0.42,
            "pct": -22.11,
            "index_pct": 77.89,
            "direction": "down"
          }
        },
        "SEM花费": {
          "vs_2h": {
            "diff": 272.49,
            "pct": 21.77,
            "index_pct": 121.77,
            "direction": "up"
          },
          "vs_yesterday": {
            "diff": 937.84,
            "pct": 160.01,
            "index_pct": 260.01,
            "direction": "up"
          }
        },
        "SEM ROI": {
          "vs_2h": {
            "diff": -0.24,
            "pct": -11.76,
            "index_pct": 88.24,
            "direction": "down"
          },
          "vs_yesterday": {
            "diff": -0.46,
            "pct": -20.35,
            "index_pct": 79.65,
            "direction": "down"
          }
        }
      },
      {
        "账户": "GMEC-Downy",
        "SKU ID": "100301903542",
        "综合花费": {
          "vs_2h": {
            "diff": 42.71,
            "pct": 4.13,
            "index_pct": 104.13,
            "direction": "up"
          },
          "vs_yesterday": {
            "diff": 514.3,
            "pct": 91.36,
            "index_pct": 191.36,
            "direction": "up"
          }
        },
        "综合ROI": {
          "vs_2h": {
            "diff": -0.06,
            "pct": -3.59,
            "index_pct": 96.41,
            "direction": "down"
          },
          "vs_yesterday": {
            "diff": -0.99,
            "pct": -38.08,
            "index_pct": 61.92,
            "direction": "down"
          }
        },
        "JST花费": {
          "vs_2h": {
            "diff": 1.08,
            "pct": 0.79,
            "index_pct": 100.79,
            "direction": "up"
          },
          "vs_yesterday": {
            "diff": 56.11,
            "pct": 68.51,
            "index_pct": 168.51,
            "direction": "up"
          }
        },
        "JST ROI": {
          "vs_2h": {
            "diff": -0.01,
            "pct": -0.47,
            "index_pct": 99.53,
            "direction": "down"
          },
          "vs_yesterday": {
            "diff": -3.31,
            "pct": -60.85,
            "index_pct": 39.15,
            "direction": "down"
          }
        },
        "SEM花费": {
          "vs_2h": {
            "diff": 41.63,
            "pct": 4.64,
            "index_pct": 104.64,
            "direction": "up"
          },
          "vs_yesterday": {
            "diff": 458.19,
            "pct": 95.26,
            "index_pct": 195.26,
            "direction": "up"
          }
        },
        "SEM ROI": {
          "vs_2h": {
            "diff": -0.07,
            "pct": -4.38,
            "index_pct": 95.62,
            "direction": "down"
          },
          "vs_yesterday": {
            "diff": -0.58,
            "pct": -27.49,
            "index_pct": 72.51,
            "direction": "down"
          }
        }
      },
      {
        "账户": "GMEC-Tide",
        "SKU ID": "100161974102",
        "综合花费": {
          "vs_2h": {
            "diff": 1057.74,
            "pct": 35.11,
            "index_pct": 135.11,
            "direction": "up"
          },
          "vs_yesterday": {
            "diff": -1011.28,
            "pct": -19.9,
            "index_pct": 80.1,
            "direction": "down"
          }
        },
        "综合ROI": {
          "vs_2h": {
            "diff": -0.04,
            "pct": -2.05,
            "index_pct": 97.95,
            "direction": "down"
          },
          "vs_yesterday": {
            "diff": 0.25,
            "pct": 15.06,
            "index_pct": 115.06,
            "direction": "up"
          }
        },
        "JST花费": {
          "vs_2h": {
            "diff": 23.78,
            "pct": 3.5,
            "index_pct": 103.5,
            "direction": "up"
          },
          "vs_yesterday": {
            "diff": 221.05,
            "pct": 45.86,
            "index_pct": 145.86,
            "direction": "up"
          }
        },
        "JST ROI": {
          "vs_2h": {
            "diff": -0.08,
            "pct": -3.43,
            "index_pct": 96.57,
            "direction": "down"
          },
          "vs_yesterday": {
            "diff": 0.43,
            "pct": 23.63,
            "index_pct": 123.63,
            "direction": "up"
          }
        },
        "SEM花费": {
          "vs_2h": {
            "diff": 1033.96,
            "pct": 44.32,
            "index_pct": 144.32,
            "direction": "up"
          },
          "vs_yesterday": {
            "diff": -1232.33,
            "pct": -26.79,
            "index_pct": 73.21,
            "direction": "down"
          }
        },
        "SEM ROI": {
          "vs_2h": {
            "diff": -0.01,
            "pct": -0.54,
            "index_pct": 99.46,
            "direction": "down"
          },
          "vs_yesterday": {
            "diff": 0.19,
            "pct": 11.59,
            "index_pct": 111.59,
            "direction": "up"
          }
        }
      },
      {
        "账户": "GMEC-Tide",
        "SKU ID": "100131766577",
        "综合花费": {
          "vs_2h": {
            "diff": 0.0,
            "pct": 0.0,
            "index_pct": 100.0,
            "direction": "neutral"
          },
          "vs_yesterday": {
            "diff": 1610.37,
            "pct": 1638.39,
            "index_pct": 1738.39,
            "direction": "up"
          }
        },
        "综合ROI": {
          "vs_2h": {
            "diff": 0.0,
            "pct": 0.0,
            "index_pct": 100.0,
            "direction": "neutral"
          },
          "vs_yesterday": {
            "diff": 0.54,
            "pct": 105.88,
            "index_pct": 205.88,
            "direction": "up"
          }
        },
        "JST花费": {
          "vs_2h": {
            "diff": 0.0,
            "pct": 0.0,
            "index_pct": 100.0,
            "direction": "neutral"
          },
          "vs_yesterday": {
            "diff": -72.02,
            "pct": -80.79,
            "index_pct": 19.21,
            "direction": "down"
          }
        },
        "JST ROI": {
          "vs_2h": {
            "diff": 0,
            "pct": 0,
            "index_pct": 0,
            "direction": "neutral"
          },
          "vs_yesterday": {
            "diff": -0.56,
            "pct": -100.0,
            "index_pct": 0.0,
            "direction": "down"
          }
        },
        "SEM花费": {
          "vs_2h": {
            "diff": 0.0,
            "pct": 0.0,
            "index_pct": 100.0,
            "direction": "neutral"
          },
          "vs_yesterday": {
            "diff": 1682.39,
            "pct": 18386.78,
            "index_pct": 18486.78,
            "direction": "up"
          }
        },
        "SEM ROI": {
          "vs_2h": {
            "diff": 0.0,
            "pct": 0.0,
            "index_pct": 100.0,
            "direction": "neutral"
          },
          "vs_yesterday": {
            "diff": 0,
            "pct": 0,
            "index_pct": 0,
            "direction": "neutral"
          }
        }
      },
      {
        "账户": "GMEC-Tide-L",
        "SKU ID": "100008794192",
        "综合花费": {
          "vs_2h": {
            "diff": 0.0,
            "pct": 0.0,
            "index_pct": 100.0,
            "direction": "neutral"
          },
          "vs_yesterday": {
            "diff": -486.68,
            "pct": -39.59,
            "index_pct": 60.41,
            "direction": "down"
          }
        },
        "综合ROI": {
          "vs_2h": {
            "diff": 0.0,
            "pct": 0.0,
            "index_pct": 100.0,
            "direction": "neutral"
          },
          "vs_yesterday": {
            "diff": -1.06,
            "pct": -33.23,
            "index_pct": 66.77,
            "direction": "down"
          }
        },
        "JST花费": {
          "vs_2h": {
            "diff": 0.0,
            "pct": 0.0,
            "index_pct": 100.0,
            "direction": "neutral"
          },
          "vs_yesterday": {
            "diff": 1.23,
            "pct": 2.29,
            "index_pct": 102.29,
            "direction": "up"
          }
        },
        "JST ROI": {
          "vs_2h": {
            "diff": 0.0,
            "pct": 0.0,
            "index_pct": 100.0,
            "direction": "neutral"
          },
          "vs_yesterday": {
            "diff": -5.19,
            "pct": -58.84,
            "index_pct": 41.16,
            "direction": "down"
          }
        },
        "SEM花费": {
          "vs_2h": {
            "diff": 0.0,
            "pct": 0.0,
            "index_pct": 100.0,
            "direction": "neutral"
          },
          "vs_yesterday": {
            "diff": -487.91,
            "pct": -41.51,
            "index_pct": 58.49,
            "direction": "down"
          }
        },
        "SEM ROI": {
          "vs_2h": {
            "diff": 0.0,
            "pct": 0.0,
            "index_pct": 100.0,
            "direction": "neutral"
          },
          "vs_yesterday": {
            "diff": -0.93,
            "pct": -31.63,
            "index_pct": 68.37,
            "direction": "down"
          }
        }
      },
      {
        "账户": "GMEC-Tide-L",
        "SKU ID": "2795972",
        "综合花费": {
          "vs_2h": {
            "diff": 244.12,
            "pct": 18.36,
            "index_pct": 118.36,
            "direction": "up"
          },
          "vs_yesterday": {
            "diff": 497.87,
            "pct": 46.26,
            "index_pct": 146.26,
            "direction": "up"
          }
        },
        "综合ROI": {
          "vs_2h": {
            "diff": 0.07,
            "pct": 3.65,
            "index_pct": 103.65,
            "direction": "up"
          },
          "vs_yesterday": {
            "diff": -0.73,
            "pct": -26.84,
            "index_pct": 73.16,
            "direction": "down"
          }
        },
        "JST花费": {
          "vs_2h": {
            "diff": 0.0,
            "pct": 0.0,
            "index_pct": 100.0,
            "direction": "neutral"
          },
          "vs_yesterday": {
            "diff": 2.98,
            "pct": 4.79,
            "index_pct": 104.79,
            "direction": "up"
          }
        },
        "JST ROI": {
          "vs_2h": {
            "diff": 0.0,
            "pct": 0.0,
            "index_pct": 100.0,
            "direction": "neutral"
          },
          "vs_yesterday": {
            "diff": -0.83,
            "pct": -13.56,
            "index_pct": 86.44,
            "direction": "down"
          }
        },
        "SEM花费": {
          "vs_2h": {
            "diff": 244.12,
            "pct": 19.3,
            "index_pct": 119.3,
            "direction": "up"
          },
          "vs_yesterday": {
            "diff": 494.89,
            "pct": 48.81,
            "index_pct": 148.81,
            "direction": "up"
          }
        },
        "SEM ROI": {
          "vs_2h": {
            "diff": 0.11,
            "pct": 6.32,
            "index_pct": 106.32,
            "direction": "up"
          },
          "vs_yesterday": {
            "diff": -0.66,
            "pct": -26.29,
            "index_pct": 73.71,
            "direction": "down"
          }
        }
      },
      {
        "账户": "GMEC-Tide-L",
        "SKU ID": "2646498",
        "综合花费": {
          "vs_2h": {
            "diff": 1124.64,
            "pct": 28.77,
            "index_pct": 128.77,
            "direction": "up"
          },
          "vs_yesterday": {
            "diff": 2663.08,
            "pct": 112.3,
            "index_pct": 212.3,
            "direction": "up"
          }
        },
        "综合ROI": {
          "vs_2h": {
            "diff": -0.21,
            "pct": -7.47,
            "index_pct": 92.53,
            "direction": "down"
          },
          "vs_yesterday": {
            "diff": -0.7,
            "pct": -21.21,
            "index_pct": 78.79,
            "direction": "down"
          }
        },
        "JST花费": {
          "vs_2h": {
            "diff": 0.0,
            "pct": 0.0,
            "index_pct": 100.0,
            "direction": "neutral"
          },
          "vs_yesterday": {
            "diff": 1.42,
            "pct": 2.24,
            "index_pct": 102.24,
            "direction": "up"
          }
        },
        "JST ROI": {
          "vs_2h": {
            "diff": 0.0,
            "pct": 0.0,
            "index_pct": 100.0,
            "direction": "neutral"
          },
          "vs_yesterday": {
            "diff": 2.54,
            "pct": 24.24,
            "index_pct": 124.24,
            "direction": "up"
          }
        },
        "SEM花费": {
          "vs_2h": {
            "diff": 1124.64,
            "pct": 29.25,
            "index_pct": 129.25,
            "direction": "up"
          },
          "vs_yesterday": {
            "diff": 2661.66,
            "pct": 115.33,
            "index_pct": 215.33,
            "direction": "up"
          }
        },
        "SEM ROI": {
          "vs_2h": {
            "diff": -0.18,
            "pct": -6.82,
            "index_pct": 93.18,
            "direction": "down"
          },
          "vs_yesterday": {
            "diff": -0.65,
            "pct": -20.9,
            "index_pct": 79.1,
            "direction": "down"
          }
        }
      },
      {
        "账户": "GMEC-Tide-L",
        "SKU ID": "100063120723",
        "综合花费": {
          "vs_2h": {
            "diff": 247.1,
            "pct": 28.81,
            "index_pct": 128.81,
            "direction": "up"
          },
          "vs_yesterday": {
            "diff": 391.72,
            "pct": 54.94,
            "index_pct": 154.94,
            "direction": "up"
          }
        },
        "综合ROI": {
          "vs_2h": {
            "diff": -0.19,
            "pct": -8.12,
            "index_pct": 91.88,
            "direction": "down"
          },
          "vs_yesterday": {
            "diff": -0.09,
            "pct": -4.02,
            "index_pct": 95.98,
            "direction": "down"
          }
        },
        "JST花费": {
          "vs_2h": {
            "diff": 0.0,
            "pct": 0.0,
            "index_pct": 100.0,
            "direction": "neutral"
          },
          "vs_yesterday": {
            "diff": 88.98,
            "pct": 71.25,
            "index_pct": 171.25,
            "direction": "up"
          }
        },
        "JST ROI": {
          "vs_2h": {
            "diff": 0.0,
            "pct": 0.0,
            "index_pct": 100.0,
            "direction": "neutral"
          },
          "vs_yesterday": {
            "diff": -0.59,
            "pct": -12.34,
            "index_pct": 87.66,
            "direction": "down"
          }
        },
        "SEM花费": {
          "vs_2h": {
            "diff": 247.1,
            "pct": 38.39,
            "index_pct": 138.39,
            "direction": "up"
          },
          "vs_yesterday": {
            "diff": 302.74,
            "pct": 51.48,
            "index_pct": 151.48,
            "direction": "up"
          }
        },
        "SEM ROI": {
          "vs_2h": {
            "diff": -0.08,
            "pct": -4.62,
            "index_pct": 95.38,
            "direction": "down"
          },
          "vs_yesterday": {
            "diff": -0.05,
            "pct": -2.94,
            "index_pct": 97.06,
            "direction": "down"
          }
        }
      },
      {
        "账户": "GMEC-Tide-L",
        "SKU ID": "100063120717",
        "综合花费": {
          "vs_2h": {
            "diff": 9.16,
            "pct": 3.61,
            "index_pct": 103.61,
            "direction": "up"
          },
          "vs_yesterday": {
            "diff": -115.48,
            "pct": -30.5,
            "index_pct": 69.5,
            "direction": "down"
          }
        },
        "综合ROI": {
          "vs_2h": {
            "diff": 0.24,
            "pct": 29.27,
            "index_pct": 129.27,
            "direction": "up"
          },
          "vs_yesterday": {
            "diff": -0.79,
            "pct": -42.7,
            "index_pct": 57.3,
            "direction": "down"
          }
        },
        "JST花费": {
          "vs_2h": {
            "diff": 9.16,
            "pct": 12.17,
            "index_pct": 112.17,
            "direction": "up"
          },
          "vs_yesterday": {
            "diff": 49.97,
            "pct": 145.05,
            "index_pct": 245.05,
            "direction": "up"
          }
        },
        "JST ROI": {
          "vs_2h": {
            "diff": 0.65,
            "pct": 34.03,
            "index_pct": 134.03,
            "direction": "up"
          },
          "vs_yesterday": {
            "diff": -3.61,
            "pct": -58.51,
            "index_pct": 41.49,
            "direction": "down"
          }
        },
        "SEM花费": {
          "vs_2h": {
            "diff": 0.0,
            "pct": 0.0,
            "index_pct": 100.0,
            "direction": "neutral"
          },
          "vs_yesterday": {
            "diff": -165.45,
            "pct": -48.08,
            "index_pct": 51.92,
            "direction": "down"
          }
        },
        "SEM ROI": {
          "vs_2h": {
            "diff": 0.0,
            "pct": 0.0,
            "index_pct": 100.0,
            "direction": "neutral"
          },
          "vs_yesterday": {
            "diff": -1.06,
            "pct": -74.65,
            "index_pct": 25.35,
            "direction": "down"
          }
        }
      }
    ],
    "formats": {
      "JST": {
        "花费": {
          "vs_2h": {
            "diff": 117.57,
            "pct": 2.26,
            "index_pct": 102.26,
            "direction": "up"
          },
          "vs_yesterday": {
            "diff": 1079.9,
            "pct": 25.54,
            "index_pct": 125.54,
            "direction": "up"
          }
        },
        "ROI": {
          "vs_2h": {
            "diff": -0.02,
            "pct": -0.56,
            "index_pct": 99.44,
            "direction": "down"
          },
          "vs_yesterday": {
            "diff": 0.35,
            "pct": 10.24,
            "index_pct": 110.24,
            "direction": "up"
          }
        }
      },
      "SEM": {
        "花费": {
          "vs_2h": {
            "diff": 7610.87,
            "pct": 25.34,
            "index_pct": 125.34,
            "direction": "up"
          },
          "vs_yesterday": {
            "diff": 15311.14,
            "pct": 68.54,
            "index_pct": 168.54,
            "direction": "up"
          }
        },
        "ROI": {
          "vs_2h": {
            "diff": -0.13,
            "pct": -6.47,
            "index_pct": 93.53,
            "direction": "down"
          },
          "vs_yesterday": {
            "diff": -0.22,
            "pct": -10.83,
            "index_pct": 89.17,
            "direction": "down"
          }
        }
      },
      "HT": {
        "花费": {
          "vs_2h": {
            "diff": 3924.97,
            "pct": 23.69,
            "index_pct": 123.69,
            "direction": "up"
          },
          "vs_yesterday": {
            "diff": 3579.9,
            "pct": 21.17,
            "index_pct": 121.17,
            "direction": "up"
          }
        },
        "ROI": {
          "vs_2h": {
            "diff": -0.14,
            "pct": -5.73,
            "index_pct": 94.27,
            "direction": "down"
          },
          "vs_yesterday": {
            "diff": 0.01,
            "pct": 0.47,
            "index_pct": 100.47,
            "direction": "up"
          }
        }
      }
    },
    "ht": {
      "GMEC-Ariel": {
        "HT花费": {
          "vs_2h": {
            "diff": 555.77,
            "pct": 42.06,
            "index_pct": 142.06,
            "direction": "up"
          },
          "vs_yesterday": {
            "diff": 713.38,
            "pct": 61.3,
            "index_pct": 161.3,
            "direction": "up"
          }
        },
        "HT ROI": {
          "vs_2h": {
            "diff": -0.33,
            "pct": -14.1,
            "index_pct": 85.9,
            "direction": "down"
          },
          "vs_yesterday": {
            "diff": -0.52,
            "pct": -20.55,
            "index_pct": 79.45,
            "direction": "down"
          }
        }
      },
      "GMEC-Ariel-L": {
        "HT花费": {
          "vs_2h": {
            "diff": 1043.55,
            "pct": 21.78,
            "index_pct": 121.78,
            "direction": "up"
          },
          "vs_yesterday": {
            "diff": 755.55,
            "pct": 14.88,
            "index_pct": 114.88,
            "direction": "up"
          }
        },
        "HT ROI": {
          "vs_2h": {
            "diff": -0.23,
            "pct": -8.46,
            "index_pct": 91.54,
            "direction": "down"
          },
          "vs_yesterday": {
            "diff": -0.07,
            "pct": -2.73,
            "index_pct": 97.27,
            "direction": "down"
          }
        }
      },
      "GMEC-Downy": {
        "HT花费": {
          "vs_2h": {
            "diff": 1327.04,
            "pct": 26.54,
            "index_pct": 126.54,
            "direction": "up"
          },
          "vs_yesterday": {
            "diff": 1109.87,
            "pct": 21.28,
            "index_pct": 121.28,
            "direction": "up"
          }
        },
        "HT ROI": {
          "vs_2h": {
            "diff": -0.08,
            "pct": -3.43,
            "index_pct": 96.57,
            "direction": "down"
          },
          "vs_yesterday": {
            "diff": 0.43,
            "pct": 23.63,
            "index_pct": 123.63,
            "direction": "up"
          }
        }
      },
      "GMEC-Tide": {
        "HT花费": {
          "vs_2h": {
            "diff": 354.08,
            "pct": 26.9,
            "index_pct": 126.9,
            "direction": "up"
          },
          "vs_yesterday": {
            "diff": 374.73,
            "pct": 28.93,
            "index_pct": 128.93,
            "direction": "up"
          }
        },
        "HT ROI": {
          "vs_2h": {
            "diff": -0.06,
            "pct": -2.9,
            "index_pct": 97.1,
            "direction": "down"
          },
          "vs_yesterday": {
            "diff": -0.18,
            "pct": -8.22,
            "index_pct": 91.78,
            "direction": "down"
          }
        }
      },
      "GMEC-Tide-L": {
        "HT花费": {
          "vs_2h": {
            "diff": 644.53,
            "pct": 15.56,
            "index_pct": 115.56,
            "direction": "up"
          },
          "vs_yesterday": {
            "diff": 626.37,
            "pct": 15.06,
            "index_pct": 115.06,
            "direction": "up"
          }
        },
        "HT ROI": {
          "vs_2h": {
            "diff": -0.05,
            "pct": -2.23,
            "index_pct": 97.77,
            "direction": "down"
          },
          "vs_yesterday": {
            "diff": -0.17,
            "pct": -7.2,
            "index_pct": 92.8,
            "direction": "down"
          }
        }
      }
    }
  }
}